openbrewerydb/__init__.py
openbrewerydb/__version__.py
openbrewerydb/constants.py
openbrewerydb/core.py
openbrewerydb/states.py
openbrewerydb-0.1.1.dist-info/METADATA
openbrewerydb-0.1.1.dist-info/RECORD
openbrewerydb-0.1.1.dist-info/WHEEL
openbrewerydb-0.1.1.dist-info/top_level.txt
