Metadata-Version: 2.1
Name: openbrewerydb
Version: 0.1.1
Summary: Python wrapper for the Open Brewery DB API
Home-page: https://github.com/jrbourbeau/openbrewerydb-python
Author: James Bourbeau
License: MIT
Platform: UNKNOWN
Provides-Extra: dev
Requires-Dist: requests
Requires-Dist: pandas
Provides-Extra: dev
Requires-Dist: flake8; extra == 'dev'
Requires-Dist: pytest; extra == 'dev'
Requires-Dist: pytest-cov; extra == 'dev'
Requires-Dist: pytest-remotedata; extra == 'dev'
Requires-Dist: sphinx; extra == 'dev'
Requires-Dist: numpydoc; extra == 'dev'
